topovision/__init__.py
topovision/__main__.py
topovision/app.py
topovision/exceptions.py
topovision/calculus/__init__.py
topovision/calculus/calculus_module.py
topovision/calculus/strategies.py
topovision/capture/__init__.py
topovision/capture/capture_module.py
topovision/capture/preprocessing.py
topovision/core/__init__.py
topovision/core/interfaces.py
topovision/core/models.py
topovision/gui/__init__.py
topovision/gui/analysis_panel.py
topovision/gui/camera_controller.py
topovision/gui/canvas_panel.py
topovision/gui/gui_module.py
topovision/gui/i18n.py
topovision/gui/plot3d_window.py
topovision/gui/theme.py
topovision/services/__init__.py
topovision/services/service_provider.py
topovision/services/task_queue.py
topovision/tests/test_calculus.py
topovision/tests/test_capture.py
topovision/tests/test_visualization.py
topovision/utils/__init__.py
topovision/utils/math.py
topovision/utils/perspective.py
topovision/utils/units.py
topovision/visualization/__init__.py
topovision/visualization/heatmap.py
topovision/visualization/overlay.py
topovision/visualization/plot3d.py
topovision/visualization/visualizers.py
topovision-0.2.1.dist-info/licenses/LICENSE
topovision-0.2.1.dist-info/licenses/NOTICE
topovision-0.2.1.dist-info/METADATA
topovision-0.2.1.dist-info/WHEEL
topovision-0.2.1.dist-info/entry_points.txt
topovision-0.2.1.dist-info/top_level.txt
topovision-0.2.1.dist-info/RECORD
