Metadata-Version: 2.4
Name: topovision
Version: 0.2.1
Summary: TopoVision - 3D Topographic Analysis System for Calculus II
Author-email: TopoVision Team <code.with.botina@gmail.com>
License:                                  Apache License
Project-URL: Homepage, https://github.com/JalaU-Capstones/topovision
Project-URL: Documentation, https://github.com/JalaU-Capstones/topovision/blob/main/README.md
Project-URL: Repository, https://github.com/JalaU-Capstones/topovision
Project-URL: Issues, https://github.com/JalaU-Capstones/topovision/issues
Keywords: computer-vision,calculus,topography,3d-analysis,education
Classifier: Development Status :: 3 - Alpha
Classifier: Intended Audience :: Education
Classifier: Intended Audience :: Science/Research
Classifier: License :: OSI Approved :: Apache Software License
Classifier: Programming Language :: Python :: 3
Classifier: Programming Language :: Python :: 3.11
Classifier: Topic :: Scientific/Engineering :: Mathematics
Classifier: Topic :: Scientific/Engineering :: Image Processing
Requires-Python: >=3.11
License-File: LICENSE
License-File: NOTICE
Requires-Dist: numpy==1.26.4
Requires-Dist: scipy==1.14.1
Requires-Dist: opencv-python==4.10.0.84
Requires-Dist: Pillow==10.3.0
Requires-Dist: matplotlib==3.9.2
Requires-Dist: python-dotenv==1.0.1
Requires-Dist: numba==0.60.0
Requires-Dist: psutil==6.1.0
Provides-Extra: dev
Requires-Dist: pytest==8.3.3; extra == "dev"
Requires-Dist: pytest-cov==5.0.0; extra == "dev"
Requires-Dist: flake8==7.1.1; extra == "dev"
Requires-Dist: black==24.8.0; extra == "dev"
Requires-Dist: isort==5.13.2; extra == "dev"
Requires-Dist: mypy==1.13.0; extra == "dev"
Requires-Dist: pre-commit==4.0.1; extra == "dev"
Requires-Dist: pdoc==14.4.0; extra == "dev"
Requires-Dist: ipython==8.28.0; extra == "dev"
Provides-Extra: light
Requires-Dist: numpy==1.26.4; extra == "light"
Requires-Dist: opencv-python-headless==4.10.0.84; extra == "light"
Requires-Dist: Pillow==10.3.0; extra == "light"
Requires-Dist: matplotlib==3.9.2; extra == "light"
Dynamic: license-file
